{
  "db_name": "PostgreSQL",
  "query": "\n            INSERT INTO users (email, password, verification_code )\n            VALUES ($1, $2, $3)\n            RETURNING *",
  "describe": {
    "columns": [
      {
        "ordinal": 0,
        "name": "id",
        "type_info": "Int4"
      },
      {
        "ordinal": 1,
        "name": "email",
        "type_info": "Varchar"
      },
      {
        "ordinal": 2,
        "name": "password",
        "type_info": "Varchar"
      },
      {
        "ordinal": 3,
        "name": "verification_code",
        "type_info": "Varchar"
      },
      {
        "ordinal": 4,
        "name": "verified",
        "type_info": "Bool"
      },
      {
        "ordinal": 5,
        "name": "created_at",
        "type_info": "Timestamp"
      },
      {
        "ordinal": 6,
        "name": "updated_at",
        "type_info": "Timestamp"
      }
    ],
    "parameters": {
      "Left": [
        "Varchar",
        "Varchar",
        "Varchar"
      ]
    },
    "nullable": [
      false,
      false,
      false,
      true,
      true,
      true,
      true
    ]
  },
  "hash": "67c9a9d1301f370ee09eec149e8b41198727101b447cefaa74305c7e7e274eed"
}
